dragonite/__init__.py
dragonite/__main__.py
dragonite/beaker.py
dragonite/cli.py
dragonite/comm.py
dragonite/conf.py
dragonite/constants.py
dragonite/coroutines.py
dragonite/dragoncon.py
dragonite/utils.py
dragonite/scrapers/__init__.py
dragonite/scrapers/base.py
dragonite/scrapers/hilton.py
dragonite/scrapers/hyatt.py
dragonite/scrapers/hyattpasskey.py
dragonite/scrapers/marriott.py
dragonite/scrapers/marriott_discount.py
dragonite-0.1.0.dist-info/DESCRIPTION.rst
dragonite-0.1.0.dist-info/METADATA
dragonite-0.1.0.dist-info/RECORD
dragonite-0.1.0.dist-info/WHEEL
dragonite-0.1.0.dist-info/entry_points.txt
dragonite-0.1.0.dist-info/metadata.json
dragonite-0.1.0.dist-info/top_level.txt
